{
  "name": "Campus Network Example",
  "baseIp": "10.100.0.0",
  "subnets": [
    {
      "id": "subnet-1",
      "name": "Engineering Building",
      "vlanId": 10,
      "expectedDevices": 100,
      "subnetInfo": {
        "expectedDevices": 100,
        "plannedDevices": 200,
        "requiredHosts": 202,
        "subnetSize": 256,
        "cidrPrefix": 24,
        "networkAddress": "10.100.0.0/24",
        "usableHosts": 254
      }
    },
    {
      "id": "subnet-2",
      "name": "Science Lab",
      "vlanId": 20,
      "expectedDevices": 75,
      "subnetInfo": {
        "expectedDevices": 75,
        "plannedDevices": 150,
        "requiredHosts": 152,
        "subnetSize": 256,
        "cidrPrefix": 24,
        "networkAddress": "10.100.1.0/24",
        "usableHosts": 254
      }
    },
    {
      "id": "subnet-3",
      "name": "Student WiFi",
      "vlanId": 30,
      "expectedDevices": 250,
      "subnetInfo": {
        "expectedDevices": 250,
        "plannedDevices": 500,
        "requiredHosts": 502,
        "subnetSize": 512,
        "cidrPrefix": 23,
        "networkAddress": "10.100.2.0/23",
        "usableHosts": 510
      }
    },
    {
      "id": "subnet-4",
      "name": "Administration",
      "vlanId": 40,
      "expectedDevices": 30,
      "subnetInfo": {
        "expectedDevices": 30,
        "plannedDevices": 60,
        "requiredHosts": 62,
        "subnetSize": 64,
        "cidrPrefix": 26,
        "networkAddress": "10.100.4.0/26",
        "usableHosts": 62
      }
    },
    {
      "id": "subnet-5",
      "name": "Guest WiFi",
      "vlanId": 50,
      "expectedDevices": 50,
      "subnetInfo": {
        "expectedDevices": 50,
        "plannedDevices": 100,
        "requiredHosts": 102,
        "subnetSize": 128,
        "cidrPrefix": 25,
        "networkAddress": "10.100.4.128/25",
        "usableHosts": 126
      }
    }
  ],
  "supernet": {
    "cidrPrefix": 21,
    "networkAddress": "10.100.0.0/21",
    "usedSize": 1216,
    "totalSize": 2048,
    "efficiency": 59.375,
    "rangeEfficiency": 100.0
  },
  "createdAt": "2024-01-01T00:00:00.000Z",
  "updatedAt": "2024-01-01T00:00:00.000Z"
}
